softapi/__init__.py
softapi/cli.py
softapi/routers/health.py
softapi/scaffold/__init__.py
softapi/scaffold/fastapi_basic.py
softapi-0.2.3.dist-info/licenses/LICENSE
softapi-0.2.3.dist-info/METADATA
softapi-0.2.3.dist-info/WHEEL
softapi-0.2.3.dist-info/entry_points.txt
softapi-0.2.3.dist-info/top_level.txt
softapi-0.2.3.dist-info/RECORD
